introrl/__init__.py
introrl/_version.py
introrl/action.py
introrl/action_coll.py
introrl/build_mdp.py
introrl/policy.py
introrl/reward.py
introrl/state.py
introrl/state_actions.py
introrl/state_actions_coll.py
introrl/state_coll.py
introrl/state_values.py
introrl/transition.py
introrl/transition_coll.py
introrl/agent_supt/__init__.py
introrl/agent_supt/action_tracker.py
introrl/agent_supt/action_value_coll.py
introrl/agent_supt/action_value_run_ave_coll.py
introrl/agent_supt/alpha_calc.py
introrl/agent_supt/change_tracker.py
introrl/agent_supt/episode.py
introrl/agent_supt/episode_maker.py
introrl/agent_supt/episode_stats.py
introrl/agent_supt/episode_summ_print.py
introrl/agent_supt/epsilon_calc.py
introrl/agent_supt/learning_tracker.py
introrl/agent_supt/model.py
introrl/agent_supt/model_state_data.py
introrl/agent_supt/model_w_pqueue.py
introrl/agent_supt/model_w_timestamp.py
introrl/agent_supt/nstep_sarsa_eval_walker.py
introrl/agent_supt/nstep_sarsa_qstar_walker.py
introrl/agent_supt/nstep_td_eval_walker.py
introrl/agent_supt/state_value_coll.py
introrl/agent_supt/state_value_run_ave_coll.py
introrl/agents/__init__.py
introrl/agents/dyna_q_agent.py
introrl/agents/dyna_qplus_agent.py
introrl/agents/priority_sweep_agent.py
introrl/agents/sa_semigrad_agent.py
introrl/agents/tabular_agent.py
introrl/black_box_sims/__init__.py
introrl/black_box_sims/blackjack_sim.py
introrl/black_box_sims/blocking_maze.py
introrl/black_box_sims/car_rental_sim.py
introrl/black_box_sims/car_rental_sim_const_rtn.py
introrl/black_box_sims/cliff_walking.py
introrl/black_box_sims/maximization_bias_mdp.py
introrl/black_box_sims/racetrack_1_sim.py
introrl/black_box_sims/racetrack_1_w_crash_sim.py
introrl/black_box_sims/racetrack_2_sim.py
introrl/black_box_sims/racetrack_legal_moves.py
introrl/black_box_sims/random_walk_1000.py
introrl/black_box_sims/sample_sim.py
introrl/black_box_sims/sim_baseline.py
introrl-0.0.6.dist-info/METADATA
introrl-0.0.6.dist-info/RECORD
introrl-0.0.6.dist-info/WHEEL
introrl-0.0.6.dist-info/entry_points.txt
introrl-0.0.6.dist-info/top_level.txt
