Metadata-Version: 2.1
Name: introrl
Version: 0.0.6
Summary: IntroRL provides a framework for exploring Reinforcement Learning. It uses the text book "Reinforcement Learning" by Sutton & Barto as a reference.
Home-page: http://introrl.readthedocs.org/en/latest/
Author: Charlie Taylor
Author-email: cet@appliedpython.com
License: GPL-3
Download-URL: https://github.com/sonofeft/IntroRL
Keywords: introrl setuptools development
Platform: any
Classifier: Development Status :: 3 - Alpha
Classifier: Operating System :: OS Independent
Classifier: Intended Audience :: Developers
Classifier: Intended Audience :: End Users/Desktop
Classifier: Topic :: Software Development :: Build Tools
Classifier: License :: OSI Approved :: GNU General Public License v3 (GPLv3)
Classifier: Programming Language :: Python :: 2
Classifier: Programming Language :: Python :: 2.7
Classifier: Programming Language :: Python :: 3
Classifier: Programming Language :: Python :: 3.5
Classifier: Programming Language :: Python :: 3.6
Classifier: Programming Language :: Python :: 3.7
Provides-Extra: test
Provides-Extra: dev
Requires-Dist: future
Provides-Extra: dev
Requires-Dist: check-manifest; extra == 'dev'
Provides-Extra: test
Requires-Dist: coverage; extra == 'test'
